{
  "workflow_id": "4a426a48-5969-4e43-80fd-7564ebc225d7",
  "pipeline_name": "Standard Pipeline",
  "stages": [
    {
      "stage_id": "stage1",
      "stage_name": "Stage 1",
      "engine_name": "Document Intelligence Engine",
      "status": "COMPLETED",
      "inputs": [
        "lesson.json"
      ],
      "outputs": [
        "lesson.json"
      ],
      "dependencies": [],
      "execution_time": 0.0,
      "errors": []
    }
  ],
  "artifacts": [
    "lesson.json"
  ],
  "started_at": "2026-07-13T13:02:28.139600",
  "finished_at": "2026-07-13T13:02:28.139600",
  "execution_time": 0.0,
  "status": "COMPLETED"
}